{"1":{"name":"Sweater Trysil Stripe Burnt Orange","price":99},
"2":{"name":"Sweater Trysil Stripe Navy","price":99},
"3":{"name":"Beanie Narvik Washed Orange","price":39},
"4":{"name":"Puffer Jacket Dundret Secret Garden","price":299},
"5":{"name":"Puffer Jacket Dundret Burnt Orange","price":249},
"6":{"name":"Cardigan Molkom Dog Shapes Beige","price":99},
"7":{"name":"Sweater Mora Dog Shapes Beige","price":89},
"8":{"name":"T-shirt Stockholm Autumn Birds Off-White","price":39},
"9":{"name":"T-shirt Stockholm Vintage Mushroom Off-White","price":34},
"10":{"name":"Boxer Briefs Kalix Dog Shapes Beige","price":24},
"11":{"name":"Puffer Jacket Dundret Leaf Green","price":249},
"12":{"name":"Puffer Jacket Dundret Grey","price":249},
"13":{"name":"T-shirt Stockholm Secret Garden","price":39},
"14":{"name":"T-shirt Stockholm Black Birds","price":39},
"15":{"name":"Hoodie Falun Color Bike Grey Melange","price":89},
"16":{"name":"Boxer Briefs Kalix Mushrooms Black","price":24},
"17":{"name":"Sweatshirt Malmoe Color Bike Charcoal","price":79},
"18":{"name":"Puffer Jacket Dundret Black","price":249},
"19":{"name":"Shirt Rute Ikat Flannel Black","price":79},
"20":{"name":"T-shirt Stockholm Ikat Black","price":39},
"21":{"name":"Shirt Rute Ikat Flannel Navy","price":79},
"22":{"name":"Sweatshirt Malmoe Base Burgundy","price":59},
"23":{"name":"Sweatshirt Malmoe Base Dark Green","price":59},
"24":{"name":"Sweater Mora Cut Mountain Multi Color","price":89},
"25":{"name":"Sweater Mora Cut Mountain Grey","price":89},
"26":{"name":"Scarf Knitted Rosse Big Check Navy","price":49},
"27":{"name":"Padded Jacket Vallentuna Corduroy Black","price":149},
"28":{"name":"Sweater Trysil Black","price":99},
"29":{"name":"Pants Ljugarn Ikat Flannel Black","price":69},
"30":{"name":"Pants Sollentuna Corduroy Black","price":99},
"31":{"name":"Padded Jacket Vallentuna Corduroy Brown","price":149},
"32":{"name":"Pants Sollentuna Corduroy Brown","price":99},
"33":{"name":"Padded Jacket Vallentuna Corduroy Deep Blue","price":149},
"34":{"name":"Pants Sollentuna Corduroy Deep Blue","price":99},
"35":{"name":"Worker Jacket Sala Corduroy Black","price":119},
"36":{"name":"Worker Jacket Sala Corduroy Brown","price":119},
"37":{"name":"Worker Jacket Sala Corduroy Deep Blue","price":119},
"38":{"name":"Jogger Lund Mushrooms Off-White","price":69},
"39":{"name":"Sweatshirt Malmoe Mushroom Grey Melange","price":79},
"40":{"name":"T-shirt Stockholm Chanterelle Dark Green","price":34}}